setup.py
utility_beta/__init__.py
utility_beta/utility_beta.py
utility_beta.egg-info/PKG-INFO
utility_beta.egg-info/SOURCES.txt
utility_beta.egg-info/dependency_links.txt
utility_beta.egg-info/not-zip-safe
utility_beta.egg-info/top_level.txt